MaRDMO/__init__.py
MaRDMO/adders.py
MaRDMO/apps.py
MaRDMO/builders.py
MaRDMO/config.py
MaRDMO/constants.py
MaRDMO/getters.py
MaRDMO/handlers.py
MaRDMO/helpers.py
MaRDMO/main.py
MaRDMO/models.py
MaRDMO/oauth2.py
MaRDMO/payload.py
MaRDMO/queries.py
MaRDMO/router.py
MaRDMO/rules.py
MaRDMO/store.py
MaRDMO/urls.py
MaRDMO/views.py
MaRDMO/algorithm/__init__.py
MaRDMO/algorithm/constants.py
MaRDMO/algorithm/handlers.py
MaRDMO/algorithm/models.py
MaRDMO/algorithm/providers.py
MaRDMO/algorithm/utils.py
MaRDMO/algorithm/worker.py
MaRDMO/algorithm/data/inversePropertyMapping.json
MaRDMO/algorithm/data/mapping.json
MaRDMO/algorithm/data/questions.json
MaRDMO/algorithm/queries/algorithm.sparql
MaRDMO/algorithm/queries/benchmark.sparql
MaRDMO/algorithm/queries/id_check.sparql
MaRDMO/algorithm/queries/problem.sparql
MaRDMO/algorithm/queries/provider_algorithm.sparql
MaRDMO/algorithm/queries/provider_benchmark.sparql
MaRDMO/algorithm/queries/provider_problem.sparql
MaRDMO/algorithm/queries/provider_publication.sparql
MaRDMO/algorithm/queries/provider_software.sparql
MaRDMO/algorithm/queries/software.sparql
MaRDMO/data/items.json
MaRDMO/data/items_staging.json
MaRDMO/data/msc2020.json
MaRDMO/data/options.json
MaRDMO/data/properties.json
MaRDMO/data/properties_staging.json
MaRDMO/model/__init__.py
MaRDMO/model/checks.py
MaRDMO/model/constants.py
MaRDMO/model/handlers.py
MaRDMO/model/models.py
MaRDMO/model/providers.py
MaRDMO/model/utils.py
MaRDMO/model/worker.py
MaRDMO/model/data/mapping.json
MaRDMO/model/data/questions.json
MaRDMO/model/queries/field.sparql
MaRDMO/model/queries/formulation-basics.sparql
MaRDMO/model/queries/formulation.sparql
MaRDMO/model/queries/model-basics.sparql
MaRDMO/model/queries/model.sparql
MaRDMO/model/queries/problem-basics.sparql
MaRDMO/model/queries/problem.sparql
MaRDMO/model/queries/quantity.sparql
MaRDMO/model/queries/task-basics.sparql
MaRDMO/model/queries/task.sparql
MaRDMO/publication/__init__.py
MaRDMO/publication/constants.py
mardmo-0.4.1.dist-info/licenses/LICENSE.md
mardmo-0.4.1.dist-info/METADATA
mardmo-0.4.1.dist-info/WHEEL
mardmo-0.4.1.dist-info/top_level.txt
mardmo-0.4.1.dist-info/RECORD
