Metadata-Version: 2.4
Name: MaRDMO
Version: 0.4.1
Summary: RDMO Plugin to document and query mathematical research data using the MaRDI infrastructure.
Author-email: Marco Reidelbach <reidelbach@zib.de>
Maintainer-email: Marco Reidelbach <reidelbach@zib.de>
License: Apache Software License
Project-URL: homepage, https://github.com/MarcoReidelbach/MaRDMO
Classifier: Intended Audience :: Science/Research
Classifier: License :: OSI Approved :: Apache Software License
Classifier: Operating System :: OS Independent
Classifier: Programming Language :: Python :: 3.10
Requires-Python: >=3.10
License-File: LICENSE.md
Requires-Dist: rdmo>=2.4.0
Dynamic: license-file
